iopathlib-0.0.5.dist-info/METADATA
iopathlib-0.0.5.dist-info/RECORD
iopathlib-0.0.5.dist-info/WHEEL
iopathlib-0.0.5.dist-info/entry_points.txt
iopathlib-0.0.5.dist-info/licenses/LICENSE
iopathlib-0.0.5.dist-info/top_level.txt
iopathlib/__init__.pyc
iopathlib/__main__.pyc
iopathlib/_download.pyc
iopathlib/_types.pyc
iopathlib/cli/__init__.pyc
iopathlib/handlers/__init__.pyc
iopathlib/handlers/__init__.pyi
iopathlib/handlers/_base.pyc
iopathlib/handlers/_io.pyc
iopathlib/handlers/_os.pyc
iopathlib/handlers/env.pyc
iopathlib/handlers/http.pyc
iopathlib/handlers/onedrive.pyc
iopathlib/handlers/wandb.pyc
iopathlib/lock/__init__.pyc
iopathlib/lock/_exceptions.pyc
iopathlib/lock/_flags.pyc
iopathlib/lock/_lock.pyc
iopathlib/lock/ops.pyc
iopathlib/manager.pyc
iopathlib/py.typed
